{
    "name": "test1234567890",
    "id": 8795,
    "type": 0,
    "public": true,
    "contentType": 6,
    "tag": null,
    "status": 0,
    "temp": false,
    "imageUrl": "",
    "cntView": 0,
    "idStr": "8795",
    "intro": "",
    "userId": 6936,
    "seq": 0,
    "categoryId": 0,
    "sphere": "en",
    "lang": "zh",
    "createDate": 1349057402000,
    "sourceUrl": null,
    "piwik": null,
    "updateDate": 1349075493000,
    "cntEpisode": 4,
    "transcodingUpdateDate": null,
    "cntSubscribe": 0,
    "playerPrefImageUrl": "",
    "userIdStr": "1-6936",
    "subscribersIdStr": null,
    "playerPrefSource": "",
    "oriName": null,
    "cntFollower": 0,
    "sorting": 0,
    "recentlyWatchedProgram": null,
    "note": null,
    "isPublic": true,
    "poolType": 0,
    "moreImageUrl": "http://i.ytimg.com/vi/qlX0JNSVUrk/mqdefault.jpg|http://i.ytimg.com/vi/qlX0JNSVUrk/mqdefault.jpg|http://i.ytimg.com/vi/qlX0JNSVUrk/mqdefault.jpg"
}
